[
    {"cnName": "哈佛大学", "enName": "Harvard University"},
    {"cnName": "斯坦福大学", "enName": "Stanford University"},
    {"cnName": "麻省理工学院", "enName": "Massachusetts Institute of Technology"},
    {"cnName": "剑桥大学", "enName": "University of Cambridge"},
    {"cnName": "加州大学-伯克利", "enName": "University of California, Berkeley"},
    {"cnName": "牛津大学", "enName": "University of Oxford"},
    {"cnName": "普林斯顿大学", "enName": "Princeton University"},
    {"cnName": "加州理工学院", "enName": "California Institute of Technology"},
    {"cnName": "哥伦比亚大学", "enName": "Columbia University"},
    {"cnName": "芝加哥大学", "enName": "University of Chicago"},
    {"cnName": "耶鲁大学", "enName": "Yale University"},
    {"cnName": "康奈尔大学", "enName": "Cornell University"},
    {"cnName": "巴黎萨克雷大学", "enName": "Paris-Saclay University"},
    {"cnName": "宾夕法尼亚大学", "enName": "University of Pennsylvania"},
    {"cnName": "加州大学-洛杉矶", "enName": "University of California, Los Angeles"},
    {"cnName": "伦敦大学学院", "enName": "University College London"},
    {"cnName": "约翰斯·霍普金斯大学", "enName": "Johns Hopkins University"},
    {"cnName": "加州大学-圣地亚哥", "enName": "University of California, San Diego"},
    {"cnName": "华盛顿大学", "enName": "University of Washington"},
    {"cnName": "加州大学-旧金山", "enName": "University of California, San Francisco"},
    {"cnName": "苏黎世联邦理工学院", "enName": "ETH Zurich"},
    {"cnName": "清华大学", "enName": "Tsinghua University"},
    {"cnName": "华盛顿大学-圣路易斯", "enName": "Washington University in St. Louis"},
    {"cnName": "北京大学", "enName": "Peking University"},
    {"cnName": "帝国理工学院", "enName": "Imperial College London"},
    {"cnName": "多伦多大学", "enName": "University of Toronto"},
    {"cnName": "浙江大学", "enName": "Zhejiang University"},
    {"cnName": "东京大学", "enName": "University of Tokyo"},
    {"cnName": "洛克菲勒大学", "enName": "Rockefeller University"},
    {"cnName": "密歇根大学-安娜堡", "enName": "University of Michigan, Ann Arbor"},
    {"cnName": "纽约大学", "enName": "New York University"},
    {"cnName": "哥本哈根大学", "enName": "University of Copenhagen"},
    {"cnName": "西北大学（埃文斯顿）", "enName": "Northwestern University (Evanston)"},
    {"cnName": "巴黎文理研究大学", "enName": "Paris Sciences et Lettres University"},
    {"cnName": "北卡罗来纳大学-教堂山", "enName": "University of North Carolina at Chapel Hill"},
    {"cnName": "威斯康星大学-麦迪逊", "enName": "University of Wisconsin–Madison"},
    {"cnName": "墨尔本大学", "enName": "University of Melbourne"},
    {"cnName": "上海交通大学", "enName": "Shanghai Jiao Tong University"},
    {"cnName": "杜克大学", "enName": "Duke University"},
    {"cnName": "爱丁堡大学", "enName": "University of Edinburgh"},
    {"cnName": "索邦大学", "enName": "Sorbonne University"},
    {"cnName": "中国科学技术大学", "enName": "University of Science and Technology of China"},
    {"cnName": "卡罗林斯卡学院", "enName": "Karolinska Institute"},
    {"cnName": "慕尼黑大学", "enName": "Ludwig Maximilian University of Munich"},
    {"cnName": "京都大学", "enName": "Kyoto University"},
    {"cnName": "德克萨斯州大学-奥斯汀", "enName": "University of Texas at Austin"},
    {"cnName": "慕尼黑工业大学", "enName": "Technical University of Munich"},
    {"cnName": "英属哥伦比亚大学", "enName": "University of British Columbia"},
    {"cnName": "明尼苏达大学-双城", "enName": "University of Minnesota, Twin Cities"},
    {"cnName": "复旦大学", "enName": "Fudan University"},
    {"cnName": "海德堡大学", "enName": "Heidelberg University"},
    {"cnName": "曼彻斯特大学", "enName": "University of Manchester"},
    {"cnName": "伦敦国王学院", "enName": "King's College London"},
    {"cnName": "德克萨斯大学西南医学中心", "enName": "UT Southwestern Medical Center"},
    {"cnName": "洛桑联邦理工学院", "enName": "École Polytechnique Fédérale de Lausanne"},
    {"cnName": "伊利诺伊大学厄巴纳-香槟", "enName": "University of Illinois Urbana-Champaign"},
    {"cnName": "乌得勒支大学", "enName": "Utrecht University"},
    {"cnName": "日内瓦大学", "enName": "University of Geneva"},
    {"cnName": "马里兰大学-大学城", "enName": "University of Maryland, College Park"},
    {"cnName": "巴黎西岱大学", "enName": "Université Paris Descartes"},
    {"cnName": "波恩大学", "enName": "University of Bonn"},
    {"cnName": "南加州大学", "enName": "University of Southern California"},
    {"cnName": "昆士兰大学", "enName": "University of Queensland"},
    {"cnName": "加州大学-圣塔芭芭拉", "enName": "University of California, Santa Barbara"},
    {"cnName": "科罗拉多大学-博尔德", "enName": "University of Colorado Boulder"},
    {"cnName": "范德堡大学", "enName": "Vanderbilt University"},
    {"cnName": "苏黎世大学", "enName": "University of Zurich"},
    {"cnName": "新加坡国立大学", "enName": "National University of Singapore"},
    {"cnName": "香港大学", "enName": "The University of Hong Kong"},
    {"cnName": "格罗宁根大学", "enName": "University of Groningen"},
    {"cnName": "魏茨曼科学研究学院", "enName": "Weizmann Institute of Science"},
    {"cnName": "中山大学", "enName": "Sun Yat-sen University"},
    {"cnName": "奥斯陆大学", "enName": "University of Oslo"},
    {"cnName": "麦吉尔大学", "enName": "McGill University"},
    {"cnName": "悉尼大学", "enName": "University of Sydney"},
    {"cnName": "加州大学-欧文", "enName": "University of California, Irvine"},
    {"cnName": "新南威尔士大学", "enName": "University of New South Wales"},
    {"cnName": "鲁汶大学（佛兰德语）", "enName": "KU Leuven"},
    {"cnName": "华中科技大学", "enName": "Huazhong University of Science and Technology"},
    {"cnName": "奥胡斯大学", "enName": "Aarhus University"},
    {"cnName": "耶路撒冷希伯来大学", "enName": "Hebrew University of Jerusalem"},
    {"cnName": "莫纳什大学", "enName": "Monash University"},
    {"cnName": "南京大学", "enName": "Nanjing University"},
    {"cnName": "俄亥俄州立大学-哥伦布", "enName": "The Ohio State University, Columbus"},
    {"cnName": "以色列理工学院", "enName": "Technion - Israel Institute of Technology"},
    {"cnName": "首尔国立大学", "enName": "Seoul National University"},
    {"cnName": "德克萨斯大学安德森肿瘤中心", "enName": "MD Anderson Cancer Center, University of Texas"},
    {"cnName": "乌普萨拉大学", "enName": "Uppsala University"},
    {"cnName": "武汉大学", "enName": "Wuhan University"},
    {"cnName": "根特大学", "enName": "Ghent University"},
    {"cnName": "沙特国王大学", "enName": "King Saud University"},
    {"cnName": "南洋理工大学", "enName": "Nanyang Technological University"},
    {"cnName": "匹兹堡大学", "enName": "University of Pittsburgh"},
    {"cnName": "中南大学", "enName": "Central South University"},
    {"cnName": "巴塞尔大学", "enName": "University of Basel"},
    {"cnName": "西安交通大学", "enName": "Xi'an Jiaotong University"},
    {"cnName": "布里斯托尔大学", "enName": "University of Bristol"},
    {"cnName": "四川大学", "enName": "Sichuan University"},
    {"cnName": "赫尔辛基大学", "enName": "University of Helsinki"},
    {"cnName": "普渡大学-西拉法叶", "enName": "Purdue University West Lafayette"},
    {"cnName": "艾克斯-马赛大学", "enName": "Aix-Marseille University"},
    {"cnName": "北京理工大学", "enName": "Beijing Institute of Technology"},
    {"cnName": "波士顿大学", "enName": "Boston University"},
    {"cnName": "布朗大学", "enName": "Brown University"},
    {"cnName": "卡内基梅隆大学", "enName": "Carnegie Mellon University"},
    {"cnName": "香港城市大学", "enName": "City University of Hong Kong"},
    {"cnName": "埃莫里大学", "enName": "Emory University"},
    {"cnName": "伊拉兹马斯大学", "enName": "Erasmus University"},
    {"cnName": "哈尔滨工业大学", "enName": "Harbin Institute of Technology"},
    {"cnName": "吉林大学", "enName": "Jilin University"},
    {"cnName": "莱顿大学", "enName": "Leiden University"},
    {"cnName": "隆德大学", "enName": "Lund University"},
    {"cnName": "梅奥诊所医学与科学学院", "enName": "Mayo Clinic College of Medicine and Science"},
    {"cnName": "麦克马斯特大学", "enName": "McMaster University"},
    {"cnName": "莫斯科国立大学", "enName": "Lomonosov Moscow State University"},
    {"cnName": "西奈山医学院", "enName": "Icahn School of Medicine at Mount Sinai"},
    {"cnName": "名古屋大学", "enName": "Nagoya University"},
    {"cnName": "西北工业大学", "enName": "Northwestern Polytechnical University"},
    {"cnName": "宾夕法尼亚州立大学-帕克", "enName": "Pennsylvania State University, Park"},
    {"cnName": "奈梅亨大学", "enName": "Radboud University Nijmegen"},
    {"cnName": "莱斯大学", "enName": "Rice University"},
    {"cnName": "罗格斯大学-新布朗斯维克", "enName": "Rutgers University–New Brunswick"},
    {"cnName": "罗马第一大学", "enName": "La Sapienza University of Rome"},
    {"cnName": "山东大学", "enName": "Shandong University"},
    {"cnName": "华南理工大学", "enName": "South China University of Technology"},
    {"cnName": "南方科技大学", "enName": "Southern University of Science and Technology"},
    {"cnName": "东南大学", "enName": "Southeast University"},
    {"cnName": "斯德哥尔摩大学", "enName": "Stockholm University"},
    {"cnName": "澳大利亚国立大学", "enName": "Australian National University"},
    {"cnName": "香港中文大学", "enName": "The Chinese University of Hong Kong"},
    {"cnName": "格拉斯哥大学", "enName": "University of Glasgow"},
    {"cnName": "西澳大利亚大学", "enName": "University of Western Australia"},
    {"cnName": "天津大学", "enName": "Tianjin University"},
    {"cnName": "格勒诺布尔大学", "enName": "University of Grenoble"},
    {"cnName": "布鲁塞尔自由大学（法语）", "enName": "Université libre de Bruxelles"},
    {"cnName": "阿尔伯塔大学", "enName": "University of Alberta"},
    {"cnName": "阿姆斯特丹大学", "enName": "University of Amsterdam"},
    {"cnName": "伯尔尼大学", "enName": "University of Bern"},
    {"cnName": "加州大学-戴维斯", "enName": "University of California, Davis"},
    {"cnName": "佛罗里达大学", "enName": "University of Florida"},
    {"cnName": "弗莱堡大学", "enName": "University of Freiburg"},
    {"cnName": "哥德堡大学", "enName": "University of Gothenburg"},
    {"cnName": "洛桑大学", "enName": "University of Lausanne"},
    {"cnName": "利物浦大学", "enName": "University of Liverpool"},
    {"cnName": "诺丁汉大学", "enName": "University of Nottingham"},
    {"cnName": "圣保罗大学", "enName": "University of São Paulo"},
    {"cnName": "斯特拉斯堡大学", "enName": "University of Strasbourg"},
    {"cnName": "犹他大学", "enName": "University of Utah"},
    {"cnName": "维也纳大学", "enName": "University of Vienna"},
    {"cnName": "华威大学", "enName": "University of Warwick"},
    {"cnName": "亚利桑那州立大学", "enName": "Arizona State University"},
    {"cnName": "北京航空航天大学", "enName": "Beihang University"},
    {"cnName": "北京师范大学", "enName": "Beijing Normal University"},
    {"cnName": "卡迪夫大学", "enName": "Cardiff University"},
    {"cnName": "凯斯西储大学", "enName": "Case Western Reserve University"},
    {"cnName": "重庆大学", "enName": "Chongqing University"},
    {"cnName": "代尔夫特理工大学", "enName": "Delft University of Technology"},
    {"cnName": "佐治亚理工学院", "enName": "Georgia Institute of Technology"},
    {"cnName": "法兰克福大学", "enName": "Goethe University Frankfurt"},
    {"cnName": "湖南大学", "enName": "Hunan University"},
    {"cnName": "印第安纳大学-布鲁明顿", "enName": "Indiana University Bloomington"},
    {"cnName": "伦敦政治经济学院", "enName": "London School of Economics and Political Science"},
    {"cnName": "伦敦大学卫生和热带医学学院", "enName": "London School of Hygiene & Tropical Medicine"},
    {"cnName": "密歇根州立大学", "enName": "Michigan State University"},
    {"cnName": "南开大学", "enName": "Nankai University"},
    {"cnName": "挪威科学技术大学", "enName": "Norwegian University of Science and Technology"},
    {"cnName": "深圳大学", "enName": "Shenzhen University"},
    {"cnName": "苏州大学", "enName": "Soochow University"},
    {"cnName": "成均馆大学", "enName": "Sungkyunkwan University"},
    {"cnName": "丹麦技术大学", "enName": "Technical University of Denmark"},
    {"cnName": "香港理工大学", "enName": "The Hong Kong Polytechnic University"},
    {"cnName": "阿德雷德大学", "enName": "University of Adelaide"},
    {"cnName": "卡尔加里大学", "enName": "University of Calgary"},
    {"cnName": "谢菲尔德大学", "enName": "University of Sheffield"},
    {"cnName": "东京工业大学", "enName": "Tokyo Institute of Technology"},
    {"cnName": "同济大学", "enName": "Tongji University"},
    {"cnName": "塔夫茨大学", "enName": "Tufts University"},
    {"cnName": "电子科技大学", "enName": "University of Electronic Science and Technology of China"},
    {"cnName": "亚利桑那大学", "enName": "University of Arizona"},
    {"cnName": "巴塞罗那大学", "enName": "University of Barcelona"},
    {"cnName": "伯明翰大学", "enName": "University of Birmingham"},
    {"cnName": "加州大学-圣克鲁兹", "enName": "University of California, Santa Cruz"},
    {"cnName": "科隆大学", "enName": "University of Cologne"},
    {"cnName": "埃克塞特大学", "enName": "University of Exeter"},
    {"cnName": "哥廷根大学", "enName": "University of Göttingen"},
    {"cnName": "利兹大学", "enName": "University of Leeds"},
    {"cnName": "美因茨大学", "enName": "University of Mainz"},
    {"cnName": "米兰大学", "enName": "University of Milan"},
    {"cnName": "蒙彼利埃大学", "enName": "University of Montpellier"},
    {"cnName": "蒙特利尔大学", "enName": "Université de Montréal"},
    {"cnName": "明斯特大学", "enName": "University of Münster"},
    {"cnName": "比萨大学", "enName": "University of Pisa"},
    {"cnName": "罗切斯特大学", "enName": "University of Rochester"},
    {"cnName": "南安普敦大学", "enName": "University of Southampton"},
    {"cnName": "图宾根大学", "enName": "University of Tübingen"},
    {"cnName": "滑铁卢大学", "enName": "University of Waterloo"},
    {"cnName": "阿姆斯特丹自由大学", "enName": "Vrije Universiteit Amsterdam"},
    {"cnName": "瓦格宁根大学", "enName": "Wageningen University"},
    {"cnName": "厦门大学", "enName": "Xiamen University"},
    {"cnName": "郑州大学", "enName": "Zhengzhou University"},
    {"cnName": "贝勒医学院", "enName": "Baylor College of Medicine"},
    {"cnName": "北京化工大学", "enName": "Beijing University of Chemical Technology"},
    {"cnName": "首都医科大学", "enName": "Capital Medical University"},
    {"cnName": "鲁汶大学（法语）", "enName": "KU Leuven (French)"},
    {"cnName": "中国农业大学", "enName": "China Agricultural University"},
    {"cnName": "中国地质大学（武汉）", "enName": "China University of Geosciences (Wuhan)"},
    {"cnName": "里昂第一大学", "enName": "University of Lyon 1"},
    {"cnName": "科罗拉多州立大学", "enName": "Colorado State University"},
    {"cnName": "科廷大学", "enName": "Curtin University"},
    {"cnName": "大连理工大学", "enName": "Dalian University of Technology"},
    {"cnName": "迪肯大学", "enName": "Deakin University"},
    {"cnName": "华东师范大学", "enName": "East China Normal University"},
    {"cnName": "福州大学", "enName": "Fuzhou University"},
    {"cnName": "乔治梅森大学", "enName": "George Mason University"},
    {"cnName": "格里菲思大学", "enName": "Griffith University"},
    {"cnName": "杜塞尔多夫大学", "enName": "Heinrich Heine University Düsseldorf"},
    {"cnName": "北海道大学", "enName": "Hokkaido University"},
    {"cnName": "香港科技大学", "enName": "Hong Kong University of Science and Technology"},
    {"cnName": "江苏大学", "enName": "Jiangsu University"},
    {"cnName": "暨南大学", "enName": "Jinan University"},
    {"cnName": "卡尔斯鲁厄理工学院", "enName": "Karlsruhe Institute of Technology"},
    {"cnName": "德国基尔大学", "enName": "Kiel University"},
    {"cnName": "阿卜杜勒阿齐兹国王大学", "enName": "King Abdulaziz University"},
    {"cnName": "阿卜杜拉国王科技大学", "enName": "King Abdullah University of Science and Technology"},
    {"cnName": "韩国科学技术院", "enName": "Korea Advanced Institute of Science and Technology"},
    {"cnName": "高丽大学", "enName": "Korea University"},
    {"cnName": "皇家理工学院", "enName": "KTH Royal Institute of Technology"},
    {"cnName": "九州大学", "enName": "Kyushu University"},
    {"cnName": "兰州大学", "enName": "Lanzhou University"},
    {"cnName": "马斯特里赫特大学", "enName": "Maastricht University"},
    {"cnName": "麦考瑞大学", "enName": "Macquarie University"},
    {"cnName": "维也纳医科大学", "enName": "Medical University of Vienna"},
    {"cnName": "南昌大学", "enName": "Nanchang University"},
    {"cnName": "南京医科大学", "enName": "Nanjing Medical University"},
    {"cnName": "南京航空航天大学", "enName": "Nanjing University of Aeronautics and Astronautics"},
    {"cnName": "台湾大学", "enName": "National Taiwan University"},
    {"cnName": "纽卡斯尔大学（英国纽卡斯尔）", "enName": "Newcastle University (UK)"},
    {"cnName": "北卡罗来纳州立大学-罗利", "enName": "North Carolina State University at Raleigh"},
    {"cnName": "东北大学（波士顿）", "enName": "Northeastern University (Boston)"},
    {"cnName": "东北大学（沈阳）", "enName": "Northeastern University (Shenyang)"},
    {"cnName": "俄勒冈卫生科学大学", "enName": "Oregon Health and Science University"},
    {"cnName": "俄勒冈州立大学", "enName": "Oregon State University"},
    {"cnName": "大阪大学", "enName": "Osaka University"},
    {"cnName": "北京协和医学院", "enName": "Peking Union Medical College"},
    {"cnName": "米兰理工大学", "enName": "Politecnico di Milano"},
    {"cnName": "伦敦大学玛丽女王学院", "enName": "Queen Mary University of London"},
    {"cnName": "皇后大学", "enName": "Queen's University"},
    {"cnName": "昆士兰科技大学", "enName": "Queensland University of Technology"},
    {"cnName": "波鸿大学", "enName": "Ruhr-University Bochum"},
    {"cnName": "亚琛工业大学", "enName": "RWTH Aachen University"},
    {"cnName": "上海大学", "enName": "Shanghai University"},
    {"cnName": "斯威本科技大学", "enName": "Swinburne University of Technology"},
    {"cnName": "柏林工业大学", "enName": "Technical University of Berlin"},
    {"cnName": "特拉维夫大学", "enName": "Tel Aviv University"},
    {"cnName": "德州农工大学", "enName": "Texas A&M University"},
    {"cnName": "奥克兰大学（新西兰）", "enName": "University of Auckland (New Zealand)"},
    {"cnName": "东北大学（仙台）", "enName": "Tohoku University"},
    {"cnName": "都柏林三一学院", "enName": "Trinity College Dublin"},
    {"cnName": "德累斯顿工业大学", "enName": "TU Dresden"},
    {"cnName": "蔚山国立科技研究所", "enName": "Ulsan National Institute of Science and Technology"},
    {"cnName": "马萨诸塞大学医学院", "enName": "University of Massachusetts Medical School"},
    {"cnName": "墨西哥国立自治大学", "enName": "Universidad Nacional Autónoma de México"},
    {"cnName": "北京科技大学", "enName": "University of Science and Technology Beijing"},
    {"cnName": "阿伯丁大学", "enName": "University of Aberdeen"},
    {"cnName": "卑尔根大学", "enName": "University of Bergen"},
    {"cnName": "博洛尼亚大学", "enName": "University of Bologna"},
    {"cnName": "波尔多大学", "enName": "University of Bordeaux"},
    {"cnName": "布宜诺斯艾利斯大学", "enName": "University of Buenos Aires"},
    {"cnName": "加州大学-河滨", "enName": "University of California, Riverside"},
    {"cnName": "开普敦大学", "enName": "University of Cape Town"},
    {"cnName": "科罗拉多大学-丹佛", "enName": "University of Colorado Denver"},
    {"cnName": "特拉华大学", "enName": "University of Delaware"},
    {"cnName": "东英吉利大学", "enName": "University of East Anglia"},
    {"cnName": "埃朗根-纽伦堡大学", "enName": "University of Erlangen-Nuremberg"},
    {"cnName": "汉堡大学", "enName": "University of Hamburg"},
    {"cnName": "休斯顿大学", "enName": "University of Houston"},
    {"cnName": "因斯布鲁克大学", "enName": "University of Innsbruck"},
    {"cnName": "莱比锡大学", "enName": "University of Leipzig"},
    {"cnName": "里斯本大学", "enName": "University of Lisbon"},
    {"cnName": "洛林大学", "enName": "University of Lorraine"},
    {"cnName": "马尼托巴大学", "enName": "University of Manitoba"},
    {"cnName": "马萨诸塞大学-阿默斯特", "enName": "University of Massachusetts Amherst"},
    {"cnName": "密苏里大学-哥伦比亚", "enName": "University of Missouri-Columbia"},
    {"cnName": "那不勒斯菲里德里克第二大学", "enName": "University of Naples Federico II"},
    {"cnName": "渥太华大学", "enName": "University of Ottawa"},
    {"cnName": "帕多瓦大学", "enName": "University of Padua"},
    {"cnName": "波尔图大学", "enName": "University of Porto"},
    {"cnName": "苏赛克斯大学", "enName": "University of Sussex"},
    {"cnName": "悉尼科技大学", "enName": "University of Technology Sydney"},
    {"cnName": "田纳西大学-诺克斯维尔", "enName": "University of Tennessee, Knoxville"},
    {"cnName": "筑波大学", "enName": "University of Tsukuba"},
    {"cnName": "都灵大学", "enName": "University of Turin"},
    {"cnName": "巴伦西亚大学", "enName": "University of Valencia"},
    {"cnName": "弗吉尼亚大学", "enName": "University of Virginia"},
    {"cnName": "维尔茨堡大学", "enName": "University of Würzburg"},
    {"cnName": "弗吉尼亚联邦（州立）大学", "enName": "Virginia Commonwealth University"},
    {"cnName": "弗吉尼亚理工学院", "enName": "Virginia Tech"},
    {"cnName": "西安大略大学", "enName": "Western University"},
    {"cnName": "武汉理工大学", "enName": "Wuhan University of Technology"},
    {"cnName": "延世大学", "enName": "Yonsei University"},
    {"cnName": "阿尔伯特·爱因斯坦医学院", "enName": "Albert Einstein College of Medicine"},
    {"cnName": "安徽大学", "enName": "Anhui University"},
    {"cnName": "巴塞罗那自治大学", "enName": "Autonomous University of Barcelona"},
    {"cnName": "马德里自治大学", "enName": "Autonomous University of Madrid"},
    {"cnName": "北京工业大学", "enName": "Beijing University of Technology"},
    {"cnName": "内盖夫本·古里安大学", "enName": "Ben-Gurion University of the Negev"},
    {"cnName": "布兰迪斯大学", "enName": "Brandeis University"},
    {"cnName": "开罗大学", "enName": "Cairo University"},
    {"cnName": "布拉格查尔斯大学", "enName": "Charles University in Prague"},
    {"cnName": "中国地质大学（北京）", "enName": "China University of Geosciences (Beijing)"},
    {"cnName": "中国石油大学（华东）", "enName": "China University of Petroleum (East China)"},
    {"cnName": "马德里康普顿斯大学", "enName": "Complutense University of Madrid"},
    {"cnName": "达尔豪斯大学", "enName": "Dalhousie University"},
    {"cnName": "达特茅斯学院", "enName": "Dartmouth College"},
    {"cnName": "杜伦大学", "enName": "Durham University"},
    {"cnName": "华东理工大学", "enName": "East China University of Science and Technology"},
    {"cnName": "里昂高等师范学校", "enName": "École Normale Supérieure de Lyon"},
    {"cnName": "佛罗里达州立大学", "enName": "Florida State University"},
    {"cnName": "广东工业大学", "enName": "Guangdong University of Technology"},
    {"cnName": "广西大学", "enName": "Guangxi University"},
    {"cnName": "汉阳大学", "enName": "Hanyang University"},
    {"cnName": "华中农业大学", "enName": "Huazhong Agricultural University"},
    {"cnName": "印第安纳大学-印第安纳波利斯", "enName": "Indiana University-Purdue University Indianapolis"},
    {"cnName": "巴黎理工学院 (IPP)", "enName": "Institut Polytechnique de Paris"},
    {"cnName": "詹姆斯库克大学", "enName": "James Cook University"},
    {"cnName": "江南大学", "enName": "Jiangnan University"},
    {"cnName": "庆应义塾大学", "enName": "Keio University"},
    {"cnName": "乐卓博大学", "enName": "La Trobe University"},
    {"cnName": "兰卡斯特大学", "enName": "Lancaster University"},
    {"cnName": "拉瓦尔大学", "enName": "Laval University"},
    {"cnName": "林雪平大学", "enName": "Linköping University"},
    {"cnName": "南京农业大学", "enName": "Nanjing Agricultural University"},
    {"cnName": "南京工业大学", "enName": "Nanjing Tech University"},
    {"cnName": "南京信息工程大学", "enName": "Nanjing University of Information Science and Technology"},
    {"cnName": "南京理工大学", "enName": "Nanjing University of Science and Technology"},
    {"cnName": "西北农林科技大学", "enName": "Northwest A&F University"},
    {"cnName": "西北大学（西安）", "enName": "Northwest University (Xi'an)"},
    {"cnName": "中国海洋大学", "enName": "Ocean University of China"},
    {"cnName": "图卢兹第三大学", "enName": "University of Toulouse III"},
    {"cnName": "浦项理工大学", "enName": "POSTECH"},
    {"cnName": "庞培法布拉大学", "enName": "Pompeu Fabra University"},
    {"cnName": "本特·阿卜杜勒拉曼大学", "enName": "Prince Sultan University"},
    {"cnName": "青岛大学", "enName": "Qingdao University"},
    {"cnName": "贝尔法斯特女王大学", "enName": "Queen's University Belfast"},
    {"cnName": "中国人民大学", "enName": "Renmin University of China"},
    {"cnName": "皇家墨尔本理工大学", "enName": "RMIT University"},
    {"cnName": "上海理工大学", "enName": "Shanghai University of Science and Technology"},
    {"cnName": "上海科技大学", "enName": "ShanghaiTech University"},
    {"cnName": "西蒙弗雷泽大学", "enName": "Simon Fraser University"},
    {"cnName": "南方医科大学", "enName": "Southern Medical University"},
    {"cnName": "纽约州立大学-石溪", "enName": "State University of New York at Stony Brook"},
    {"cnName": "瑞典农业科学大学", "enName": "Swedish University of Agricultural Sciences"},
    {"cnName": "乔治华盛顿大学", "enName": "The George Washington University"},
    {"cnName": "图卢兹第一大学", "enName": "University of Toulouse I"},
    {"cnName": "雅典大学", "enName": "University of Athens"},
    {"cnName": "德克萨斯大学卫生科学中心-休斯顿", "enName": "University of Texas Health Science Center at Houston"},
    {"cnName": "科克大学学院", "enName": "University College Cork"},
    {"cnName": "都柏林大学学院", "enName": "University College Dublin"},
    {"cnName": "安特卫普大学", "enName": "University of Antwerp"},
    {"cnName": "辛辛那提大学", "enName": "University of Cincinnati"},
    {"cnName": "康涅狄格大学-斯道思", "enName": "University of Connecticut-Storrs"},
    {"cnName": "杜伊斯堡-埃森大学", "enName": "University of Duisburg-Essen"},
    {"cnName": "佛罗伦萨大学", "enName": "University of Florence"},
    {"cnName": "热那亚大学", "enName": "University of Genoa"},
    {"cnName": "格拉纳达大学", "enName": "University of Granada"},
    {"cnName": "夏威夷大学-马诺阿", "enName": "University of Hawaii at Manoa"},
    {"cnName": "伊利诺大学-芝加哥", "enName": "University of Illinois at Chicago"},
    {"cnName": "爱荷华大学", "enName": "University of Iowa"},
    {"cnName": "耶拿大学", "enName": "University of Jena"},
    {"cnName": "堪萨斯大学-劳伦斯", "enName": "University of Kansas at Lawrence"},
    {"cnName": "肯塔基大学", "enName": "University of Kentucky"},
    {"cnName": "莱斯特大学", "enName": "University of Leicester"},
    {"cnName": "列日大学", "enName": "University of Liège"},
    {"cnName": "里尔大学", "enName": "University of Lille"},
    {"cnName": "澳门大学", "enName": "University of Macau"},
    {"cnName": "马尔堡大学", "enName": "University of Marburg"},
    {"cnName": "马里兰大学-巴尔的摩", "enName": "University of Maryland, Baltimore"},
    {"cnName": "迈阿密大学", "enName": "University of Miami"},
    {"cnName": "米兰比可卡大学", "enName": "University of Milano-Bicocca"},
    {"cnName": "内布拉斯加大学-林肯", "enName": "University of Nebraska-Lincoln"},
    {"cnName": "圣母玛利亚大学", "enName": "University of Notre Dame"},
    {"cnName": "波茨坦大学", "enName": "University of Potsdam"},
    {"cnName": "雷根斯堡大学", "enName": "University of Regensburg"},
    {"cnName": "南佛罗里达大学", "enName": "University of South Florida"},
    {"cnName": "南丹麦大学", "enName": "University of Southern Denmark"},
    {"cnName": "圣安德鲁斯大学", "enName": "University of St Andrews"},
    {"cnName": "斯图加特大学", "enName": "University of Stuttgart"},
    {"cnName": "塔斯马尼亚大学", "enName": "University of Tasmania"},
    {"cnName": "巴斯克大学", "enName": "University of the Basque Country"},
    {"cnName": "金山大学", "enName": "University of the Golden Coast"},
    {"cnName": "特兰托大学", "enName": "University of Trento"},
    {"cnName": "乌尔姆大学", "enName": "University of Ulm"},
    {"cnName": "维多利亚大学（加拿大）", "enName": "University of Victoria (Canada)"},
    {"cnName": "卧龙冈大学", "enName": "University of Wollongong"},
    {"cnName": "约克大学（约克）", "enName": "University of York"},
    {"cnName": "维也纳工业大学", "enName": "Vienna University of Technology"},
    {"cnName": "布鲁塞尔自由大学（佛兰德语）", "enName": "Vrije Universiteit Brussel (Flemish)"},
    {"cnName": "西悉尼大学", "enName": "Western Sydney University"},
    {"cnName": "扬州大学", "enName": "Yangzhou University"},
    {"cnName": "浙江工业大学", "enName": "Zhejiang University of Technology"},
    {"cnName": "奥尔堡大学", "enName": "Aalborg University"},
    {"cnName": "阿尔托大学", "enName": "Aalto University"},
    {"cnName": "巴依兰大学", "enName": "Bayreuth University"},
    {"cnName": "查尔姆斯理工大学", "enName": "Chalmers University of Technology"},
    {"cnName": "中国医药大学", "enName": "China Medical University"},
    {"cnName": "中国矿业大学", "enName": "China University of Mining and Technology"},
    {"cnName": "纽约城市大学研究生院和大学中心", "enName": "City University of New York Graduate Center"},
    {"cnName": "德雷塞尔大学", "enName": "Drexel University"},
    {"cnName": "埃因霍温工业大学", "enName": "Eindhoven University of Technology"},
    {"cnName": "弗林德斯大学", "enName": "Flinders University"},
    {"cnName": "广州医科大学", "enName": "Guangzhou Medical University"},
    {"cnName": "广州大学", "enName": "Guangzhou University"},
    {"cnName": "海南大学", "enName": "Hainan University"},
    {"cnName": "汉诺威医学院", "enName": "Hannover Medical School"},
    {"cnName": "合肥工业大学", "enName": "Hefei University of Technology"},
    {"cnName": "河南大学", "enName": "Henan University"},
    {"cnName": "河海大学", "enName": "Hohai University"},
    {"cnName": "印度科学理工学院", "enName": "Indian Institute of Science and Technology"},
    {"cnName": "伊斯坦布尔大学", "enName": "Istanbul University"},
    {"cnName": "克拉科夫雅盖隆大学", "enName": "Jagiellonian University in Krakow"},
    {"cnName": "哈立德国王大学", "enName": "King Khalid University"},
    {"cnName": "昆明理工大学", "enName": "Kunming University of Science and Technology"},
    {"cnName": "庆熙大学", "enName": "Kyung Hee University"},
    {"cnName": "庆北国立大学", "enName": "Kyungpook National University"},
    {"cnName": "汉诺威大学", "enName": "Leibniz University Hannover"},
    {"cnName": "路易斯安那州立大学-巴吞鲁日", "enName": "Louisiana State University - Baton Rouge"},
    {"cnName": "澳门科技大学", "enName": "Macau University of Science and Technology"},
    {"cnName": "马萨里克大学", "enName": "Masaryk University"},
    {"cnName": "南京林业大学", "enName": "Nanjing Forestry University"},
    {"cnName": "南京师范大学", "enName": "Nanjing Normal University"},
    {"cnName": "南京邮电大学", "enName": "Nanjing University of Posts and Telecommunications"},
    {"cnName": "台湾成功大学", "enName": "National Cheng Kung University"},
    {"cnName": "台湾清华大学", "enName": "National Tsing Hua University"},
    {"cnName": "台湾阳明交通大学", "enName": "National Yang Ming Chiao Tung University"},
    {"cnName": "中国人民解放军国防科技大学", "enName": "National University of Defense Technology"},
    {"cnName": "宁波大学", "enName": "Ningbo University"},
    {"cnName": "冲绳科学技术大学院大学", "enName": "Okinawa Institute of Science and Technology"},
    {"cnName": "瓦伦西亚理工大学", "enName": "Polytechnic University of Valencia"},
    {"cnName": "釜山国立大学", "enName": "Pusan National University"},
    {"cnName": "萨尔大学", "enName": "Saarland University"},
    {"cnName": "圣彼得堡国立大学", "enName": "Saint Petersburg State University"},
    {"cnName": "圣保罗州立大学", "enName": "São Paulo State University"},
    {"cnName": "华南农业大学", "enName": "South China Agricultural University"},
    {"cnName": "西南交通大学", "enName": "Southwest Jiaotong University"},
    {"cnName": "纽约州立大学-布法罗", "enName": "State University of New York at Buffalo"},
    {"cnName": "斯坦陵布什大学", "enName": "Stellenbosch University"},
    {"cnName": "塔伊夫大学", "enName": "Taif University"},
    {"cnName": "达姆施塔特工业大学", "enName": "Technical University of Darmstadt"},
    {"cnName": "德黑兰医科大学", "enName": "Tehran University of Medical Sciences"},
    {"cnName": "坦普尔大学", "enName": "Temple University"},
    {"cnName": "德克萨斯技术大学", "enName": "Texas Tech University"},
    {"cnName": "邓迪大学", "enName": "University of Dundee"},
    {"cnName": "佐治亚大学", "enName": "University of Georgia"},
    {"cnName": "纽卡斯尔大学（澳大利亚纽卡斯尔）", "enName": "University of Newcastle, Australia"},
    {"cnName": "雷丁大学", "enName": "University of Reading"},
    {"cnName": "圣心天主教大学", "enName": "Università Cattolica del Sacro Cuore"},
    {"cnName": "南里奥格兰德联邦大学", "enName": "Universidade Federal do Rio Grande do Sul"},
    {"cnName": "南卡罗来纳大学-哥伦比亚", "enName": "University of South Carolina - Columbia"},
    {"cnName": "德克萨斯大学医学部-加尔维斯顿", "enName": "University of Texas Medical Branch - Galveston"},
    {"cnName": "阿拉巴马大学-伯明翰", "enName": "University of Alabama at Birmingham"},
    {"cnName": "阿威罗大学", "enName": "University of Aveiro"},
    {"cnName": "巴里大学", "enName": "University of Bari"},
    {"cnName": "拜罗伊特大学", "enName": "University of Bayreuth"},
    {"cnName": "贝尔格莱德大学", "enName": "University of Belgrade"},
    {"cnName": "坎皮纳斯州立大学", "enName": "University of Campinas"},
    {"cnName": "坎特伯雷大学", "enName": "University of Canterbury"},
    {"cnName": "卡塔尼亚大学", "enName": "University of Catania"},
    {"cnName": "中佛罗里达大学", "enName": "University of Central Florida"},
    {"cnName": "智利大学", "enName": "University of Chile"},
    {"cnName": "蔚蓝海岸大学", "enName": "University of Côte d'Azur"},
    {"cnName": "哈勒-维滕贝格大学", "enName": "University of Halle-Wittenberg"},
    {"cnName": "约翰内斯堡大学", "enName": "University of Johannesburg"},
    {"cnName": "肯特大学", "enName": "University of Kent"},
    {"cnName": "马来亚大学", "enName": "University of Malaya"},
    {"cnName": "俄勒冈大学", "enName": "University of Oregon"},
    {"cnName": "奥塔哥大学", "enName": "University of Otago"},
    {"cnName": "奥卢大学", "enName": "University of Oulu"},
    {"cnName": "帕维亚大学", "enName": "University of Pavia"},
    {"cnName": "雷恩大学", "enName": "University of Rennes"},
    {"cnName": "罗马第二大学", "enName": "University of Rome Tor Vergata"},
    {"cnName": "萨斯喀彻温大学", "enName": "University of Saskatchewan"},
    {"cnName": "塞维利亚大学", "enName": "University of Seville"},
    {"cnName": "南澳大学", "enName": "University of South Australia"},
    {"cnName": "萨里大学", "enName": "University of Surrey"},
    {"cnName": "塞格德大学", "enName": "University of Szeged"},
    {"cnName": "德黑兰大学", "enName": "University of Tehran"},
    {"cnName": "图尔库大学", "enName": "University of Turku"},
    {"cnName": "特文特大学", "enName": "University of Twente"},
    {"cnName": "蔚山大学", "enName": "University of Ulsan"},
    {"cnName": "佛蒙特大学", "enName": "University of Vermont"},
    {"cnName": "华沙大学", "enName": "University of Warsaw"},
    {"cnName": "萨格勒布大学", "enName": "University of Zagreb"},
    {"cnName": "德克萨斯大学卫生科学中心-圣安东尼奥", "enName": "University of Texas Health Science Center - San Antonio"},
    {"cnName": "犹他州立大学", "enName": "Utah State University"},
    {"cnName": "惠灵顿维多利亚大学", "enName": "Victoria University of Wellington"},
    {"cnName": "圣拉斐尔生命健康大学", "enName": "Università Vita-Salute San Raffaele"},
    {"cnName": "华盛顿州立大学-普尔曼", "enName": "Washington State University - Pullman"},
    {"cnName": "西安电子科技大学", "enName": "Xidian University"},
    {"cnName": "约克大学（多伦多）", "enName": "York University (Toronto)"},
    {"cnName": "云南大学", "enName": "Yunnan University"}
]
          
      
  